process_engine_client/__init__.py
process_engine_client/core/__init__.py
process_engine_client/core/base_client.py
process_engine_client/core/loop_helper.py
process_engine_client/external_task/__init__.py
process_engine_client/external_task/external_task_client.py
process_engine_client/external_task/external_task_handler.py
process_engine_client/process_control/__init__.py
process_engine_client/process_control/process_control_client.py
process_engine_client/process_control/start_callback_type.py
process_engine_client/user_task/__init__.py
process_engine_client/user_task/user_task_client.py
tests/__init__.py
tests/helper_aiohttp.py
tests/core/__init__.py
tests/core/test_base_client.py
tests/core/test_loop_helper.py
tests/process_control/__init__.py
tests/process_control/test_process_control_client.py
process_engine_client-0.3.dist-info/METADATA
process_engine_client-0.3.dist-info/WHEEL
process_engine_client-0.3.dist-info/top_level.txt
process_engine_client-0.3.dist-info/RECORD
