Metadata-Version: 2.1
Name: process-engine-client
Version: 0.3
Summary: A Client for an process-engine.io hosted workflow engine.
Home-page: https://github.com/moellenbeck/process_engine_client
Author: 5Minds IT-Solutions GmbH & Co. KG
Author-email: processengine@5minds.de
License: UNKNOWN
Keywords: workflow-engine processengine client bpmn
Platform: UNKNOWN
Classifier: Programming Language :: Python :: 3
Classifier: License :: OSI Approved :: MIT License
Classifier: Operating System :: OS Independent
